LICENSE
README.md
setup.py
ndefcdf/__init__.py
ndefcdf/baserecord.py
ndefcdf/config.py
ndefcdf/lnpay.py
ndefcdf/lnwithdrawal.py
ndefcdf.egg-info/PKG-INFO
ndefcdf.egg-info/SOURCES.txt
ndefcdf.egg-info/dependency_links.txt
ndefcdf.egg-info/requires.txt
ndefcdf.egg-info/top_level.txt