Metadata-Version: 2.1
Name: ndefcdf
Version: 0.0.3
Summary: NDEF Crypto Data Format
Home-page: https://github.com/agama-point/ndefcdf
Author: Petr Kracik
Author-email: petrkr@petrkr.net
License: Apache Software License
Platform: UNKNOWN
Classifier: Programming Language :: Python :: 3
Classifier: License :: OSI Approved :: Apache Software License
Classifier: Operating System :: OS Independent
Classifier: Development Status :: 1 - Planning
Requires-Python: >=3.4
License-File: LICENSE
